rsyncdirector_deploy/__init__.py
rsyncdirector_deploy/argparser.py
rsyncdirector_deploy/consts.py
rsyncdirector_deploy/main.py
rsyncdirector_deploy/configs/etc/logrotate.d/rsyncdirector.tmpl
rsyncdirector_deploy/configs/etc/rsyncdirector/rsyncdirector.env.tmpl
rsyncdirector_deploy/configs/etc/rsyncdirector/rsyncdirector.sh.tmpl
rsyncdirector_deploy/configs/etc/systemd/system/rsyncdirector@.service.tmpl
rsyncdirector_deploy/deploy/__init__.py
rsyncdirector_deploy/deploy/configs.py
rsyncdirector_deploy/deploy/install.py
rsyncdirector_deploy/deploy/linux.py
rsyncdirector_deploy/deploy/python.py
rsyncdirector_deploy/deploy/rsyncdirector.py
rsyncdirector_deploy/deploy/ssh.py
rsyncdirector_deploy/deploy/utils.py
rsyncdirector_deploy-0.0.4.dist-info/LICENSE
rsyncdirector_deploy-0.0.4.dist-info/METADATA
rsyncdirector_deploy-0.0.4.dist-info/WHEEL
rsyncdirector_deploy-0.0.4.dist-info/entry_points.txt
rsyncdirector_deploy-0.0.4.dist-info/top_level.txt
rsyncdirector_deploy-0.0.4.dist-info/RECORD
