Metadata-Version: 2.2
Name: rsyncdirector_deploy
Version: 0.0.4
Summary: Deployment tools for the rsyncdirector module
Author-email: Ryan Chapin <rchapin@nbinteractive.com>
License: This software is released under the Revised BSD License.
Project-URL: Homepage, https://github.com/rchapin/rsyncdirector/deploy
Project-URL: readme, https://github.com/rchapin/rsyncdirector/deploy/README.md
Classifier: Programming Language :: Python :: 3
Classifier: License :: OSI Approved :: BSD License
Classifier: Operating System :: POSIX :: Linux
Requires-Python: >=3.13
License-File: LICENSE
Requires-Dist: bcrypt==5.0.0
Requires-Dist: certifi==2025.11.12
Requires-Dist: cffi==2.0.0
Requires-Dist: charset-normalizer==3.4.4
Requires-Dist: cryptography==46.0.3
Requires-Dist: decorator==5.2.1
Requires-Dist: deprecated==1.3.1
Requires-Dist: fabric==3.2.2
Requires-Dist: idna==3.11
Requires-Dist: invoke==2.2.1
Requires-Dist: paramiko==4.0.0
Requires-Dist: pycparser==2.23
Requires-Dist: pynacl==1.6.1
Requires-Dist: pyyaml==6.0.1
Requires-Dist: requests==2.32.5
Requires-Dist: urllib3==2.5.0
Requires-Dist: wrapt==2.0.1
